optionsfactory/__init__.py
optionsfactory/_utils.py
optionsfactory/_version.py
optionsfactory/checks.py
optionsfactory/optionsfactory.py
optionsfactory/withmeta.py
optionsfactory/tests/__init__.py
optionsfactory/tests/test_check_utilities.py
optionsfactory/tests/test_mutableoptions.py
optionsfactory/tests/test_options.py
optionsfactory/tests/test_withmeta.py
optionsfactory-1.0.11.dist-info/LICENSE
optionsfactory-1.0.11.dist-info/METADATA
optionsfactory-1.0.11.dist-info/WHEEL
optionsfactory-1.0.11.dist-info/top_level.txt
optionsfactory-1.0.11.dist-info/RECORD
