Metadata-Version: 2.1
Name: optionsfactory
Version: 1.0.11
Summary: Handles user-provided options with flexible defaults, documentation and checking
Home-page: https://github.com/johnomotani/optionsfactory
Author: John Omotani
Author-email: john.omotani@cantab.net
License: OSI Approved :: GNU General Public License v3 or later (GPLv3+)
Classifier: Programming Language :: Python :: 3
Classifier: License :: OSI Approved :: BSD License
Classifier: Operating System :: OS Independent
Requires-Python: >=3.6
License-File: LICENSE
Provides-Extra: yaml
Requires-Dist: PyYAML (>=5.1) ; extra == 'yaml'
